taskitor/__init__.py
taskitor/commands.py
taskitor/main.py
taskitor/storage.py
taskitor/task.py
taskitor-0.1.0.dist-info/METADATA
taskitor-0.1.0.dist-info/WHEEL
taskitor-0.1.0.dist-info/entry_points.txt
taskitor-0.1.0.dist-info/top_level.txt
taskitor-0.1.0.dist-info/RECORD
