Metadata-Version: 2.4
Name: taskitor
Version: 0.1.0
Summary: A simple task tracker CLI using Python and Rich.
Home-page: https://github.com/PyTorDev/taskitor
Author: Aitor
Classifier: Programming Language :: Python :: 3
Classifier: License :: OSI Approved :: MIT License
Classifier: Operating System :: OS Independent
Requires-Python: >=3.10
Requires-Dist: rich
Dynamic: author
Dynamic: classifier
Dynamic: description
Dynamic: description-content-type
Dynamic: home-page
Dynamic: requires-dist
Dynamic: requires-python
Dynamic: summary
